README.rst
setup.cfg
setup.py
netbox_netprod_importer/__init__.py
netbox_netprod_importer/__main__.py
netbox_netprod_importer/config.py
netbox_netprod_importer/devices_list.py
netbox_netprod_importer/exceptions.py
netbox_netprod_importer/importer.py
netbox_netprod_importer/push.py
netbox_netprod_importer/tools.py
netbox_netprod_importer.egg-info/PKG-INFO
netbox_netprod_importer.egg-info/SOURCES.txt
netbox_netprod_importer.egg-info/dependency_links.txt
netbox_netprod_importer.egg-info/entry_points.txt
netbox_netprod_importer.egg-info/not-zip-safe
netbox_netprod_importer.egg-info/requires.txt
netbox_netprod_importer.egg-info/top_level.txt
netbox_netprod_importer/vendors/__init__.py
netbox_netprod_importer/vendors/base.py
netbox_netprod_importer/vendors/constants.py
netbox_netprod_importer/vendors/cisco/__init__.py
netbox_netprod_importer/vendors/cisco/base.py
netbox_netprod_importer/vendors/cisco/constants.py
netbox_netprod_importer/vendors/cisco/ios.py
netbox_netprod_importer/vendors/cisco/nxos.py
netbox_netprod_importer/vendors/juniper/__init__.py
netbox_netprod_importer/vendors/juniper/base.py
netbox_netprod_importer/vendors/juniper/constants.py