Metadata-Version: 1.1
Name: netbox-netprod-importer
Version: 0.0.1
Summary: Microservice import into netbox devices in production
Home-page: https://gitlab.infra.online.net/network/netbox_netprod_importer
Author: Scaleway
Author-email: contact@scaleway.com
License: UNKNOWN
Keywords: netbox_netprod_importer
Platform: UNKNOWN
Classifier: Development Status :: 2 - Pre-Alpha
Classifier: Intended Audience :: Developers
Classifier: Natural Language :: English
Classifier: Programming Language :: Python :: 3
Classifier: Programming Language :: Python :: 3.4
Classifier: Programming Language :: Python :: 3.5
Classifier: Programming Language :: Python :: 3.6
